agent_guard_core/__init__.py
agent_guard_core/api/__init__.py
agent_guard_core/api/identity/__init__.py
agent_guard_core/api/identity/consts.py
agent_guard_core/api/identity/handler.py
agent_guard_core/api/identity/resources/login_error.html
agent_guard_core/api/identity/resources/login_success.html
agent_guard_core/api/sia/__init__.py
agent_guard_core/api/sia/handler.py
agent_guard_core/api/sia/models.py
agent_guard_core/cli/__init__.py
agent_guard_core/cli/cli.py
agent_guard_core/cli/idp_cli.py
agent_guard_core/cli/mcp_proxy_cli.py
agent_guard_core/cli/secrets_cli.py
agent_guard_core/cli/sia_cli.py
agent_guard_core/cli.md
agent_guard_core/cli.py
agent_guard_core/credentials/README.md
agent_guard_core/credentials/__init__.py
agent_guard_core/credentials/aws_secrets_manager_provider.py
agent_guard_core/credentials/conjur_secrets_provider.py
agent_guard_core/credentials/enum.py
agent_guard_core/credentials/environment_manager.py
agent_guard_core/credentials/file_secrets_provider.py
agent_guard_core/credentials/gcp_secrets_manager_provider.py
agent_guard_core/credentials/secrets_provider.py
agent_guard_core/model/secret_uri.py
agent_guard_core/proxy/__init__.py
agent_guard_core/proxy/audited_proxy.py
agent_guard_core/proxy/proxy_utils.py
agent_guard_core/sia.md
agent_guard_core/utils/__init__.py
agent_guard_core/utils/env.py
agent_guard_core/utils/flavor_manager.py
agent_guard_core/utils/mcp_config_wizard.py
agent_guard_core-0.1.34.dist-info/LICENSE
agent_guard_core-0.1.34.dist-info/METADATA
agent_guard_core-0.1.34.dist-info/NOTICES.txt
agent_guard_core-0.1.34.dist-info/WHEEL
agent_guard_core-0.1.34.dist-info/entry_points.txt
agent_guard_core-0.1.34.dist-info/RECORD
